text_quality_analyzer/__init__.py
text_quality_analyzer/language_detector.py
text_quality_analyzer/meaningfulness_checker.py
text_quality_analyzer/structure_analyzer.py
text_quality_analyzer/text_profile.py
text_quality_analyzer/utils.py
text_quality_analyzer-0.1.2.dist-info/licenses/LICENSE
text_quality_analyzer-0.1.2.dist-info/licenses/NOTICE
text_quality_analyzer-0.1.2.dist-info/METADATA
text_quality_analyzer-0.1.2.dist-info/WHEEL
text_quality_analyzer-0.1.2.dist-info/top_level.txt
text_quality_analyzer-0.1.2.dist-info/RECORD
