Metadata-Version: 2.4
Name: text-quality-analyzer
Version: 0.1.2
Summary: Universal text analysis module for detecting language, meaningfulness, and structure
Home-page: https://github.com/yourusername/text-quality-analyzer
Author: Text Quality Analyzer Team
Author-email: LifeAiTools Team <dev@muid.io>
License: Apache-2.0
Classifier: Development Status :: 3 - Alpha
Classifier: Intended Audience :: Developers
Classifier: Topic :: Text Processing :: Linguistic
Classifier: License :: OSI Approved :: Apache Software License
Classifier: Programming Language :: Python :: 3
Classifier: Programming Language :: Python :: 3.9
Classifier: Programming Language :: Python :: 3.10
Classifier: Programming Language :: Python :: 3.11
Requires-Python: >=3.9
License-File: LICENSE
License-File: NOTICE
Requires-Dist: langid>=1.1.6
Requires-Dist: textstat>=0.7.3
Requires-Dist: wordfreq>=3.0.0
Provides-Extra: dev
Requires-Dist: pytest>=7.4.0; extra == "dev"
Requires-Dist: pytest-cov>=4.1.0; extra == "dev"
Requires-Dist: black>=23.0.0; extra == "dev"
Requires-Dist: mypy>=1.5.0; extra == "dev"
Requires-Dist: flake8>=6.0.0; extra == "dev"
Dynamic: author
Dynamic: home-page
Dynamic: license-file
Dynamic: requires-python
